publish
setup.cfg
setup.py
tests/test1.py
tests/test2.py
yospaceCDS/__init__.py
yospaceCDS/ws.py
yospaceCDS.egg-info/PKG-INFO
yospaceCDS.egg-info/SOURCES.txt
yospaceCDS.egg-info/dependency_links.txt
yospaceCDS.egg-info/requires.txt
yospaceCDS.egg-info/top_level.txt