Metadata-Version: 1.0
Name: yospaceCDS
Version: 1.1.0
Summary: Yospace CDS Webservice Client
Home-page: http://www.yospace.com/index.php/cds_main.html
Author: Yospace Systems
Author-email: systems@yospace.com
License: Distribute Freely
Platform: UNKNOWN
Classifier: Development Status :: 5 - Production/Stable
Classifier: Intended Audience :: Developers
Classifier: License :: Freely Distributable
Classifier: Operating System :: Unix
Classifier: Operating System :: POSIX :: Linux
Classifier: Operating System :: POSIX :: SunOS/Solaris
Classifier: Operating System :: Microsoft
Classifier: Operating System :: Microsoft :: Windows
Classifier: Operating System :: MacOS
Classifier: Programming Language :: Python
Classifier: Topic :: Multimedia :: Video :: Conversion
Classifier: Topic :: Software Development :: Libraries :: Python Modules
